uainsight/__init__.py
uainsight/core.py
uainsight/integrations/__init__.py
uainsight/integrations/django.py
uainsight/integrations/fastapi.py
uainsight/integrations/flask.py
uainsight/utils.py
uainsight-0.1.0.dist-info/LICENSE
uainsight-0.1.0.dist-info/METADATA
uainsight-0.1.0.dist-info/WHEEL
uainsight-0.1.0.dist-info/RECORD
