Metadata-Version: 2.1
Name: uainsight
Version: 0.1.0
Summary: Inspired by the express-useragent package, A User-Agent parser for Python with integrations for FastAPI, Django, and Flask
Home-page: https://joongi007.github.io/uainsight/
License: MIT
Keywords: user-agent,parser,fastapi,django,flask
Author: joongi007
Author-email: joongi007@naver.com
Requires-Python: >=3.9,<4.0
Classifier: License :: OSI Approved :: MIT License
Classifier: Programming Language :: Python :: 3
Classifier: Programming Language :: Python :: 3.9
Classifier: Programming Language :: Python :: 3.10
Classifier: Programming Language :: Python :: 3.11
Classifier: Programming Language :: Python :: 3.12
Project-URL: Repository, https://github.com/joongi007/uainsight
